clouDL/__init__.py
clouDL/analyze.py
clouDL/earlystop.py
clouDL/main.py
clouDL/manager.py
clouDL_utils/__init__.py
clouDL_utils/archive.py
clouDL_utils/downloader.py
clouDL_utils/gcp_interactions.py
clouDL_utils/hyperparameters.py
clouDL_utils/progress.py
clouDL_utils/startup.sh
clouDL_utils/strings.py
clouDL_utils/user_files/README.md
clouDL_utils/user_files/access_token
clouDL_utils/user_files/configs.json
clouDL_utils/user_files/hyperparameters.json
clouDL_utils/user_files/quick_start.sh
clouDL_utils/user_files/user_startup.sh
clouDL-0.1.1.dist-info/METADATA
clouDL-0.1.1.dist-info/WHEEL
clouDL-0.1.1.dist-info/entry_points.txt
clouDL-0.1.1.dist-info/top_level.txt
clouDL-0.1.1.dist-info/RECORD
