Metadata-Version: 2.1
Name: clouDL
Version: 0.1.1
Summary: Automatically manages a cluster of VMs in GCP to train and hyperparamter tune DL models that use PyTorch.
Home-page: UNKNOWN
Author: Shuhao Lai
Author-email: Shuhaolai18@gmail.com
License: UNKNOWN
Platform: UNKNOWN
Requires-Dist: google-api-python-client
Requires-Dist: google-cloud-storage
Requires-Dist: matplotlib
Requires-Dist: pathlib
